README.md
setup.py
src/flask_github_webhook.py
src/flask_github_webhook.egg-info/PKG-INFO
src/flask_github_webhook.egg-info/SOURCES.txt
src/flask_github_webhook.egg-info/dependency_links.txt
src/flask_github_webhook.egg-info/requires.txt
src/flask_github_webhook.egg-info/top_level.txt